<?xml version = '1.0' encoding = 'UTF-8'?>
<Diagram class="oracle.dbtools.crest.swingui.datatypes.DPVDataTypes" id="3DF9CCBC-3A88-A1C6-BC45-09BE30161D0E">
<createdBy>jjk17</createdBy>
<modifiedBy>jjk17</modifiedBy>
<createdTime>2020-07-17 05:00:54 UTC</createdTime>
<autoRoute>false</autoRoute>
<boxInbox>true</boxInbox>
<showLegend>false</showLegend>
<showLabels>true</showLabels>
<showRelAttributes>false</showRelAttributes>
<gridEnabled>false</gridEnabled>
<showGrid>false</showGrid>
<diagramColor>-1</diagramColor>
<display>false</display>
<notation>1</notation>
<objectViews>
<OView class="oracle.dbtools.crest.swingui.datatypes.TVStructuredType" oid="47E390DE-0671-C4B1-8428-0F45CBEE18F8" otype="StructuredType" vid="9F5F1C34-A2E0-73D2-C700-D037BE0AC043">
<hideElementsInCurrentOnly>false</hideElementsInCurrentOnly>
<bounds x="20" y="20" width="108" height="39"/>
</OView>
<OView class="oracle.dbtools.crest.swingui.datatypes.TVStructuredType" oid="F72C39E0-D1CA-8821-2AD7-A1E95A37D3D1" otype="StructuredType" vid="1288AC9E-883F-663B-4ADE-C22EAFC008C8">
<hideElementsInCurrentOnly>false</hideElementsInCurrentOnly>
<bounds x="178" y="20" width="78" height="39"/>
</OView>
</objectViews>
</Diagram>